numpay/__init__.py
numpay/numpay.py
numpay-0.0.8.dist-info/METADATA
numpay-0.0.8.dist-info/WHEEL
numpay-0.0.8.dist-info/top_level.txt
numpay-0.0.8.dist-info/RECORD
