Metadata-Version: 2.1
Name: numpay
Version: 0.0.8
Summary: helo
Home-page: UNKNOWN
Author: aaaroo
Author-email: aaro@gmail.com
License: UNKNOWN
Platform: UNKNOWN
Requires-Python: >=2.1
